oarepo_tokens/__init__.py
oarepo_tokens/config.py
oarepo_tokens/constants.py
oarepo_tokens/ext.py
oarepo_tokens/models.py
oarepo_tokens/permissions.py
oarepo_tokens/tasks.py
oarepo_tokens/version.py
oarepo_tokens/views.py
oarepo_tokens/alembic/171069d4f96a_create_oarepo_tokens_table.py
oarepo_tokens/alembic/6346f97f7bc1_switch_to_rec_uuid.py
oarepo_tokens/alembic/c8488e82f7d6_idexes_added.py
oarepo_tokens/alembic/fcd82d97a4c0_create_oarepo_tokens_table.py
tests/__init__.py
tests/conftest.py
tests/test_oarepo_tokens.py
tests/api/__init__.py
tests/api/conftest.py
tests/api/constants.py
tests/api/helpers.py
tests/api/marshmallow.py
tests/api/test_models.py
tests/api/test_rest.py
tests/api/jsonschemas/__init__.py
oarepo_tokens-0.1.10.dist-info/AUTHORS.rst
oarepo_tokens-0.1.10.dist-info/LICENSE
oarepo_tokens-0.1.10.dist-info/METADATA
oarepo_tokens-0.1.10.dist-info/WHEEL
oarepo_tokens-0.1.10.dist-info/entry_points.txt
oarepo_tokens-0.1.10.dist-info/top_level.txt
oarepo_tokens-0.1.10.dist-info/RECORD
