Metadata-Version: 2.1
Name: oarepo-tokens
Version: 0.1.10
Summary: OArepo module that adds support for tokens
Home-page: https://github.com/oarepo/oarepo-tokens
Author: Tomas Hlava
Author-email: hlava@cesnet.cz
License: MIT
Keywords: invenio oarepo tokens
Platform: any
Classifier: Environment :: Web Environment
Classifier: Intended Audience :: Developers
Classifier: License :: OSI Approved :: MIT License
Classifier: Operating System :: OS Independent
Classifier: Programming Language :: Python
Classifier: Topic :: Internet :: WWW/HTTP :: Dynamic Content
Classifier: Topic :: Software Development :: Libraries :: Python Modules
Classifier: Programming Language :: Python :: 3
Classifier: Programming Language :: Python :: 3.6
Classifier: Programming Language :: Python :: 3.7
Classifier: Programming Language :: Python :: 3.8
Classifier: Programming Language :: Python :: 3.9
Classifier: Development Status :: 1 - Planning
License-File: LICENSE
License-File: AUTHORS.rst
Requires-Dist: oarepo-records-draft
Requires-Dist: oarepo-validate
Requires-Dist: oarepo-references
Requires-Dist: oarepo-fsm
Requires-Dist: oarepo-multilingual
Requires-Dist: oarepo-s3
Requires-Dist: flask (~=1.1.0)
Requires-Dist: oarepo-actions
Provides-Extra: all
Requires-Dist: oarepo[tests] (~=3.3.0) ; extra == 'all'
Requires-Dist: pydocstyle ; extra == 'all'
Requires-Dist: isort ; extra == 'all'
Requires-Dist: oarepo-records-draft ; extra == 'all'
Requires-Dist: oarepo-validate ; extra == 'all'
Requires-Dist: oarepo-references ; extra == 'all'
Requires-Dist: oarepo-fsm ; extra == 'all'
Requires-Dist: oarepo-multilingual ; extra == 'all'
Requires-Dist: moto ; extra == 'all'
Requires-Dist: oarepo-s3 ; extra == 'all'
Requires-Dist: flask (~=1.1.0) ; extra == 'all'
Requires-Dist: oarepo-actions ; extra == 'all'
Provides-Extra: tests
Requires-Dist: oarepo[tests] (~=3.3.0) ; extra == 'tests'
Requires-Dist: pydocstyle ; extra == 'tests'
Requires-Dist: isort ; extra == 'tests'
Requires-Dist: oarepo-records-draft ; extra == 'tests'
Requires-Dist: oarepo-validate ; extra == 'tests'
Requires-Dist: oarepo-references ; extra == 'tests'
Requires-Dist: oarepo-fsm ; extra == 'tests'
Requires-Dist: oarepo-multilingual ; extra == 'tests'
Requires-Dist: moto ; extra == 'tests'
Requires-Dist: oarepo-s3 ; extra == 'tests'
Requires-Dist: flask (~=1.1.0) ; extra == 'tests'
Requires-Dist: oarepo-actions ; extra == 'tests'
